[
  {
    "tema": "Recetas",
    "titulo": "Tarta de Manzana",
    "url_imagen": "https://ejemplo.com/imagen_tarta_manzana.jpg",
    "nivel": "Intermedio"
  },
  {
    "tema": "Recetas",
    "titulo": "Ensalada César",
    "url_imagen": "https://ejemplo.com/imagen_ensalada_cesar.jpg",
    "nivel": "Fácil"
  },
  {
    "tema": "Recetas",
    "titulo": "Nuevo usuario",
    "url_imagen": "https://ejemplo.com/imagen_ensalada_cesar.jpg",
    "nivel": "Fácil"
  },
  {
    "tema": "Viajes",
    "titulo": "París",
    "url_imagen": "https://ejemplo.com/imagen_paris.jpg",
    "nivel": "Avanzado"
  },
  {
    "tema": "Viajes",
    "titulo": "Tokio",
    "url_imagen": "https://ejemplo.com/imagen_tokio.jpg",
    "nivel": "Intermedio"
  },
  {
    "tema": "Deportes",
    "titulo": "Fútbol",
    "url_imagen": "https://ejemplo.com/imagen_futbol.jpg",
    "nivel": "Fácil"
  }
]
